JUC/__init__.py
JUC/calculateKey.py
JUC/exceptions.py
JUC/main.py
JUC-0.0.5.dist-info/METADATA
JUC-0.0.5.dist-info/WHEEL
JUC-0.0.5.dist-info/top_level.txt
JUC-0.0.5.dist-info/RECORD
