Metadata-Version: 2.1
Name: JUC
Version: 0.0.5
Summary: A simple Unicode based text crypter
Home-page: UNKNOWN
Author: JProgrammer-it
Author-email: <jprogrammer.mail@pm.me>
License: UNKNOWN
Keywords: python,cryptography,encryption,decryption,text,file,unicode,python3
Platform: UNKNOWN
Classifier: Development Status :: 1 - Planning
Classifier: Intended Audience :: Developers
Classifier: Programming Language :: Python :: 3
Classifier: Operating System :: Unix
Classifier: Operating System :: MacOS :: MacOS X
Classifier: Operating System :: Microsoft :: Windows
